cache_register/__init__.py
cache_register/apps.py
cache_register/register.py
cache_register-0.1.1.dist-info/METADATA
cache_register-0.1.1.dist-info/WHEEL
cache_register-0.1.1.dist-info/top_level.txt
cache_register-0.1.1.dist-info/RECORD
