Metadata-Version: 2.2
Name: cache_register
Version: 0.1.1
Summary: Add your description here
Author: Aran Borkum
Requires-Python: >=3.12
Requires-Dist: django>=5.1.6
